schulplots/__init__.py
schulplots/converter.py
schulplots/figure_description.py
schulplots/functions.py
schulplots/lines.py
schulplots/main.py
schulplots/py.typed
schulplots/saxes.py
schulplots/sfigure.py
schulplots/sgraph.py
schulplots/spoints.py
schulplots/text.py
schulplots/types.py
schulplots/_attic/schulplots.py
schulplots/utils/math_expression.py
schulplots/utils/math_parser.py
schulplots-0.9.9.dist-info/licenses/LICENSE
schulplots-0.9.9.dist-info/METADATA
schulplots-0.9.9.dist-info/WHEEL
schulplots-0.9.9.dist-info/entry_points.txt
schulplots-0.9.9.dist-info/top_level.txt
schulplots-0.9.9.dist-info/RECORD
