Metadata-Version: 2.4
Name: schulplots
Version: 0.9.9
Summary: schulplots -- an educational tool to create plots of functions, styled as expected by undergraduate students in German schools.
Author-email: Hans Aschauer <schulplots@hans-aschauer.de>
License: MIT
Project-URL: Homepage, https://github.com/HansAschauer/schulplots/
Project-URL: Documentation, https://schulplots.hans-aschauer.de
Keywords: education,plotting,teaching,publication
Classifier: Intended Audience :: Education
Classifier: Programming Language :: Python :: 3.11
Classifier: Framework :: Matplotlib
Requires-Python: <3.13,>=3.9
License-File: LICENSE
Requires-Dist: matplotlib>=3.7.1
Requires-Dist: pyparsing>=3.1.1
Requires-Dist: numpy>=1.23.1
Requires-Dist: cattrs>=23.1.2
Requires-Dist: PyYAML>=6.0.1
Provides-Extra: dev
Requires-Dist: mkdocs>=1.5.3; extra == "dev"
Requires-Dist: mkdocs-material>=9.4.8; extra == "dev"
Requires-Dist: icecream>=2.1.3; extra == "dev"
Requires-Dist: ipykernel>=6.26.0; extra == "dev"
Dynamic: license-file
